S3Library/__init__.py
rf_s3library-0.5a3.dist-info/METADATA
rf_s3library-0.5a3.dist-info/WHEEL
rf_s3library-0.5a3.dist-info/top_level.txt
rf_s3library-0.5a3.dist-info/RECORD
