Metadata-Version: 2.1
Name: rf-s3library
Version: 0.5a3
Summary: Robot Framework Library for AWS S3 support.
Home-page: https://github.com/MainSystemDev/rf-s3libray
Author: Shiela Buitizon
Author-email: shiela.buitizon@mnltechnology.com
License: MIT
Platform: any
Classifier: Development Status :: 5 - Production/Stable
Classifier: License :: OSI Approved :: MIT License
Classifier: Operating System :: OS Independent
Classifier: Programming Language :: Python :: 3
Classifier: Topic :: Software Development :: Testing
Classifier: Framework :: Robot Framework
Classifier: Framework :: Robot Framework :: Library
Requires-Dist: boto3 (==1.34.69)
Requires-Dist: robotframework (>=3.0)
